LICENSE
MANIFEST.in
setup.py
emotient/__init__.py
emotient/api.py
emotient/emotient_client.py
emotient/error.py
emotient/http_client.py
emotient/managers.py
emotient/mixins.py
emotient/models.py
emotient/resources.py
emotient/utils.py
emotient.egg-info/PKG-INFO
emotient.egg-info/SOURCES.txt
emotient.egg-info/dependency_links.txt
emotient.egg-info/pbr.json
emotient.egg-info/requires.txt
emotient.egg-info/top_level.txt