Metadata-Version: 1.1
Name: emotient
Version: 0.1.0
Summary: Use the Emotient Analytics APIs from Python
Home-page: https://github.com/emotient/emotient-python
Author: Emotient
Author-email: support@emotient.com
License: MIT
Keywords: emotient
Platform: UNKNOWN
Classifier: Development Status :: 3 - Alpha
Classifier: Intended Audience :: Developers
Classifier: Topic :: Software Development :: Libraries :: Python Modules
Classifier: License :: OSI Approved :: MIT License
Classifier: Programming Language :: Python :: 2.7
